juno/__init__.py
juno/cli.py
juno/config.py
juno/data.py
juno/simulator.py
juno/web.py
juno/data/P4C2.model
juno/data/P5C3.model
juno/data/P6C4.model
juno/data/R103.model
juno/data/R94.model
juno/data/R95.model
juno/data/assembly_summary.pkl
juno/tools/fasterq-dump
juno/tools/fasterq-dump-orig.3.0.0
juno/tools/fasterq-dump.3
juno/tools/fasterq-dump.3.0.0
juno/tools/pbsim
juno/tools/vdb-config
juno/tools/vdb-config.3
juno/tools/vdb-config.3.0.0
bio_juno-1.0.0.dist-info/LICENSE
bio_juno-1.0.0.dist-info/METADATA
bio_juno-1.0.0.dist-info/WHEEL
bio_juno-1.0.0.dist-info/entry_points.txt
bio_juno-1.0.0.dist-info/top_level.txt
bio_juno-1.0.0.dist-info/RECORD
