Metadata-Version: 2.1
Name: bio-juno
Version: 1.0.0
Summary: Juno: read data generator
Home-page: https://github.com/hunglin59638/juno
Author: hunglin
Author-email: hunglin59638@gmail.com
Maintainer: hunglin
Maintainer-email: hunglin59638@gmail.com
License: UNKNOWN
Platform: UNKNOWN
Requires-Python: >=3.8,<4.0
License-File: LICENSE
Requires-Dist: pysradb (<2.0.0,>=1.3.0)
Requires-Dist: streamlit-aggrid (<0.3.0,>=0.2.3)
Requires-Dist: streamlit (<2.0.0,>=1.9.2)
